llmquery/__init__.py
llmquery/__main__.py
llmquery/llmquery.py
llmquery-0.2.0.data/data/llmquery-templates/basic-query.yaml
llmquery-0.2.0.data/data/llmquery-templates/check-code-secrets.yaml
llmquery-0.2.0.data/data/llmquery-templates/check-is-valid-secret.yaml
llmquery-0.2.0.data/data/llmquery-templates/detect-natural-language.yaml
llmquery-0.2.0.data/data/llmquery-templates/detect-pii.yml
llmquery-0.2.0.data/data/llmquery-templates/detect-prompt-injection.yaml
llmquery-0.2.0.data/data/llmquery-templates/detect-security-vulnerabilities.yaml
llmquery-0.2.0.data/data/llmquery-templates/find-book-author-name.yaml
llmquery-0.2.0.data/data/llmquery-templates/generate-jira-ticket.yaml
llmquery-0.2.0.data/data/llmquery-templates/grammarly-assistant.yaml
llmquery-0.2.0.data/data/llmquery-templates/pr-reviews.yaml
llmquery-0.2.0.data/data/llmquery-templates/pr-summary.yaml
llmquery-0.2.0.data/data/llmquery-templates/template.yaml
llmquery-0.2.0.data/data/llmquery-templates/translate-natural-language.yaml
llmquery-0.2.0.dist-info/licenses/LICENSE.md
providers/__init__.py
providers/anthropic_lib/__init__.py
providers/anthropic_lib/anthropic_claude.py
providers/aws_bedrock_lib/__init__.py
providers/aws_bedrock_lib/aws_bedrock.py
providers/deepseek_lib/__init__.py
providers/deepseek_lib/deepseek.py
providers/github_ai_models_lib/__init__.py
providers/github_ai_models_lib/github_ai_models.py
providers/google_gemini_lib/__init__.py
providers/google_gemini_lib/google_gemini.py
providers/mistral_lib/__init__.py
providers/mistral_lib/mistral.py
providers/ollama_lib/__init__.py
providers/ollama_lib/ollama.py
providers/openai_lib/__init__.py
providers/openai_lib/openai.py
query_parser/__init__.py
query_parser/query_parser.py
llmquery-0.2.0.dist-info/METADATA
llmquery-0.2.0.dist-info/WHEEL
llmquery-0.2.0.dist-info/entry_points.txt
llmquery-0.2.0.dist-info/top_level.txt
llmquery-0.2.0.dist-info/RECORD
