Metadata-Version: 2.4
Name: llmquery
Version: 0.2.0
Summary: A package for querying various LLM providers
Home-page: https://github.com/mazen160/llmquery
Author: Mazin Ahmed
Author-email: mazin@mazinahmed.net
Classifier: Programming Language :: Python :: 3
Classifier: License :: OSI Approved :: MIT License
Classifier: Operating System :: OS Independent
Requires-Python: >=3.6
License-File: LICENSE.md
Requires-Dist: pyyaml>=6.0.2
Requires-Dist: jinja2>=3.1.5
Requires-Dist: requests>=2.32.3
Requires-Dist: rich>=13.9.4
Requires-Dist: setuptools>=65.5.1
Requires-Dist: boto3>=1.35.98
Requires-Dist: tiktoken
Dynamic: author
Dynamic: author-email
Dynamic: classifier
Dynamic: description
Dynamic: description-content-type
Dynamic: home-page
Dynamic: license-file
Dynamic: requires-dist
Dynamic: requires-python
Dynamic: summary
